kgtk_wukunhuan/__init__.py
kgtk_wukunhuan/__main__.py
kgtk_wukunhuan/cli_argparse.py
kgtk_wukunhuan/cli_entry.py
kgtk_wukunhuan/configure_kgtk_notebooks.py
kgtk_wukunhuan/dependencies.py
kgtk_wukunhuan/exceptions.py
kgtk_wukunhuan/files_config.py
kgtk_wukunhuan/functions.py
kgtk_wukunhuan/generator.py
kgtk_wukunhuan/kgtkformat.py
kgtk_wukunhuan/nomalizer.py
kgtk_wukunhuan/cli/__dummy.py
kgtk_wukunhuan/cli/__init__.py
kgtk_wukunhuan/cli/__ticker.py
kgtk_wukunhuan/cli/add_id.py
kgtk_wukunhuan/cli/build-kgtk-search-input.py
kgtk_wukunhuan/cli/calc.py
kgtk_wukunhuan/cli/cat.py
kgtk_wukunhuan/cli/clean_data.py
kgtk_wukunhuan/cli/community-detection.py
kgtk_wukunhuan/cli/compact.py
kgtk_wukunhuan/cli/connected-components.py
kgtk_wukunhuan/cli/convert-embeddings-format.py
kgtk_wukunhuan/cli/count.py
kgtk_wukunhuan/cli/expand.py
kgtk_wukunhuan/cli/explode.py
kgtk_wukunhuan/cli/export_gt.py
kgtk_wukunhuan/cli/export_neo4j.py
kgtk_wukunhuan/cli/export_wikidata.py
kgtk_wukunhuan/cli/extract_wikidata_json.py
kgtk_wukunhuan/cli/filter.py
kgtk_wukunhuan/cli/generate_mediawiki_jsons.py
kgtk_wukunhuan/cli/generate_wikidata_triples.py
kgtk_wukunhuan/cli/graph_statistics.py
kgtk_wukunhuan/cli/head.py
kgtk_wukunhuan/cli/html.py
kgtk_wukunhuan/cli/ifempty.py
kgtk_wukunhuan/cli/ifexists.py
kgtk_wukunhuan/cli/ifnotempty.py
kgtk_wukunhuan/cli/ifnotexists.py
kgtk_wukunhuan/cli/implode.py
kgtk_wukunhuan/cli/import_atomic.py
kgtk_wukunhuan/cli/import_concept_pairs.py
kgtk_wukunhuan/cli/import_conceptnet.py
kgtk_wukunhuan/cli/import_framenet.py
kgtk_wukunhuan/cli/import_ntriples.py
kgtk_wukunhuan/cli/import_visualgenome.py
kgtk_wukunhuan/cli/import_wikidata.py
kgtk_wukunhuan/cli/import_wordnet.py
kgtk_wukunhuan/cli/join.py
kgtk_wukunhuan/cli/lexicalize.py
kgtk_wukunhuan/cli/lift.py
kgtk_wukunhuan/cli/md.py
kgtk_wukunhuan/cli/normalize.py
kgtk_wukunhuan/cli/normalize_nodes.py
kgtk_wukunhuan/cli/paths.py
kgtk_wukunhuan/cli/query.py
kgtk_wukunhuan/cli/reachable_nodes.py
kgtk_wukunhuan-1.5.4.dist-info/METADATA
kgtk_wukunhuan-1.5.4.dist-info/WHEEL
kgtk_wukunhuan-1.5.4.dist-info/entry_points.txt
kgtk_wukunhuan-1.5.4.dist-info/top_level.txt
kgtk_wukunhuan-1.5.4.dist-info/RECORD
