Metadata-Version: 2.1
Name: kgtk_wukunhuan
Version: 1.5.4
Home-page: https://github.com/WuKunhuan/kgtk
Author: ISI CKGs | Wu Kunhuan
Requires-Dist: sh ==1.14.3
Requires-Dist: attrs
Requires-Dist: lz4
Requires-Dist: iso-639
Requires-Dist: pycountry
Requires-Dist: shortuuid
Requires-Dist: rdflib ==6.1.1
Requires-Dist: rdflib-jsonld ==0.6.2
Requires-Dist: pyshacl >=0.19.0
Requires-Dist: rfc3986
Requires-Dist: thinc
Requires-Dist: plac ==1.1.3
Requires-Dist: parsley >=1.3
Requires-Dist: peewee >=3.14.10
Requires-Dist: odictliteral
Requires-Dist: unidecode
Requires-Dist: scikit-learn
Requires-Dist: loguru
Requires-Dist: mypy
Requires-Dist: rltk
Requires-Dist: seaborn
Requires-Dist: SPARQLWrapper
Requires-Dist: tqdm
Requires-Dist: simplejson
Requires-Dist: pyrallel.lib ==0.0.9
Requires-Dist: redis
Requires-Dist: dill >=0.3.2
Requires-Dist: usc-isi-i2-mgzip >=0.2.1.3
Requires-Dist: h5py
